[
  {
    "name": "theme_info",
    "theme_name": "VCN Store",
    "theme_version": "1.0.0",
    "theme_author": "VCN",
    "theme_documentation_url": "",
    "theme_support_url": ""
  },
  {
    "name": "Colors",
    "settings": [
      {
        "type": "color",
        "id": "color_background",
        "label": "Background",
        "default": "#0a0a0f"
      },
      {
        "type": "color",
        "id": "color_accent",
        "label": "Accent",
        "default": "#8B5CF6"
      }
    ]
  }
]
